setup.py
cammackr1_stage_a.egg-info/PKG-INFO
cammackr1_stage_a.egg-info/SOURCES.txt
cammackr1_stage_a.egg-info/dependency_links.txt
cammackr1_stage_a.egg-info/top_level.txt
csc440_robby_stage_a/__init__.py
csc440_robby_stage_a/stage_a_search.py