Metadata-Version: 1.0
Name: cammackr1-stage-a
Version: 2.8
Summary: CSC440 Stage A
Home-page: https://www.robby.com
Author: rlcammack
Author-email: cammackr1@nku.edu
License: Robby
Platform: UNKNOWN
